flake8_aaa/__about__.py
flake8_aaa/__init__.py
flake8_aaa/act_node.py
flake8_aaa/block.py
flake8_aaa/checker.py
flake8_aaa/conf.py
flake8_aaa/exceptions.py
flake8_aaa/function.py
flake8_aaa/helpers.py
flake8_aaa/line_markers.py
flake8_aaa/types.py
flake8_aaa/visitors.py
flake8_aaa-0.17.1.2.dist-info/licenses/LICENSE
flake8_aaa-0.17.1.2.dist-info/METADATA
flake8_aaa-0.17.1.2.dist-info/WHEEL
flake8_aaa-0.17.1.2.dist-info/entry_points.txt
flake8_aaa-0.17.1.2.dist-info/top_level.txt
flake8_aaa-0.17.1.2.dist-info/RECORD
