Metadata-Version: 2.4
Name: flake8-aaa
Version: 0.17.1.2
Summary: A Flake8 plugin that checks Python tests follow the Arrange-Act-Assert pattern
Home-page: https://github.com/jamescooke/flake8-aaa
Author: James Cooke
Author-email: github@jamescooke.info
License: MIT
Classifier: Development Status :: 4 - Beta
Classifier: Framework :: Flake8
Classifier: Intended Audience :: Developers
Classifier: License :: OSI Approved :: MIT License
Classifier: Programming Language :: Python :: 3 :: Only
Classifier: Programming Language :: Python :: 3
Classifier: Programming Language :: Python :: 3.8
Classifier: Programming Language :: Python :: 3.9
Classifier: Programming Language :: Python :: 3.10
Classifier: Programming Language :: Python :: 3.11
Classifier: Programming Language :: Python :: 3.12
Classifier: Programming Language :: Python :: 3.13
Classifier: Programming Language :: Python
Requires-Python: >=3.8
License-File: LICENSE
Requires-Dist: asttokens>=2
Requires-Dist: flake8>=3
Dynamic: author
Dynamic: author-email
Dynamic: classifier
Dynamic: description
Dynamic: home-page
Dynamic: license
Dynamic: license-file
Dynamic: requires-dist
Dynamic: requires-python
Dynamic: summary
